__init__.py
finetune.py
merge.py
transqlate/__init__.py
transqlate/embedding_utils.py
transqlate/inference.py
transqlate/sql_transform.py
transqlate/cli/__init__.py
transqlate/cli/cli.py
transqlate/schema_pipeline/__init__.py
transqlate/schema_pipeline/extractor.py
transqlate/schema_pipeline/formatter.py
transqlate/schema_pipeline/graph.py
transqlate/schema_pipeline/orchestrator.py
transqlate/schema_pipeline/selector.py
transqlate/utils/hardware.py
transqlate-1.0.0.dist-info/licenses/LICENSE
transqlate-1.0.0.dist-info/METADATA
transqlate-1.0.0.dist-info/WHEEL
transqlate-1.0.0.dist-info/entry_points.txt
transqlate-1.0.0.dist-info/top_level.txt
transqlate-1.0.0.dist-info/RECORD
