Metadata-Version: 2.4
Name: transqlate
Version: 1.0.0
Summary: Natural Language to SQL CLI powered by a fine-tuned LLM.
Author-email: Shaurya Sethi <shauryaswapansethi@gmail.com>
License: MIT License
Requires-Python: >=3.8
License-File: LICENSE
Requires-Dist: cx_oracle==8.3.0
Requires-Dist: networkx==3.4.2
Requires-Dist: numpy==2.2.5
Requires-Dist: pandas==2.2.3
Requires-Dist: openpyxl==3.1.5
Requires-Dist: psycopg2_binary==2.9.10
Requires-Dist: pwinput==1.0.3
Requires-Dist: pyodbc==5.2.0
Requires-Dist: pytest==8.3.5
Requires-Dist: rapidfuzz==3.13.0
Requires-Dist: rich==14.0.0
Requires-Dist: sentence_transformers==4.1.0
Requires-Dist: transformers==4.51.3
Requires-Dist: accelerate==1.7.0
Requires-Dist: bitsandbytes==0.46.0
Requires-Dist: huggingface_hub==0.31.2
Dynamic: license-file
